allure/__init__.py
allure/__main__.py
allure_cmd-0.0.5.dist-info/METADATA
allure_cmd-0.0.5.dist-info/WHEEL
allure_cmd-0.0.5.dist-info/dependency_links.txt
allure_cmd-0.0.5.dist-info/entry_points.txt
allure_cmd-0.0.5.dist-info/top_level.txt
allure_cmd-0.0.5.dist-info/RECORD
