Metadata-Version: 2.1
Name: allure-cmd
Version: 0.0.5
Summary: A simple commandline app for Allure report generation
Home-page: https://github.com/SergeyPirogov/allure-cmd
Author: Sergey Pirogov
Author-email: semen4ik20@gmail.com
License: MIT
Platform: UNKNOWN
Classifier: License :: OSI Approved :: MIT License
Classifier: Programming Language :: Python :: 3
Classifier: Programming Language :: Python :: 3.6
Requires-Python: >=3.6
